suave_deletes/__init__.py
suave_deletes/mixins.py
suave_deletes/queries.py
suave_deletes/sessions.py
tests/__init__.py
tests/test_suave_deletes.py
suave_deletes-0.1.5.dist-info/LICENSE
suave_deletes-0.1.5.dist-info/METADATA
suave_deletes-0.1.5.dist-info/WHEEL
suave_deletes-0.1.5.dist-info/top_level.txt
suave_deletes-0.1.5.dist-info/RECORD
