Metadata-Version: 2.1
Name: suave_deletes
Version: 0.1.5
Summary: A simple soft delete implementation for sqlalchemy
Home-page: https://github.com/stefanFramework/suave_deletes
Author: Stefan Framework
Classifier: Programming Language :: Python :: 3
Classifier: License :: OSI Approved :: MIT License
Classifier: Operating System :: OS Independent
Requires-Python: >=3.6
License-File: LICENSE
Requires-Dist: SQLAlchemy >=2.0.0
